simplesoc/__init__.py
simplesoc/data.py
simplesoc/functions.py
simplesoc-0.5.3.dist-info/METADATA
simplesoc-0.5.3.dist-info/WHEEL
simplesoc-0.5.3.dist-info/top_level.txt
simplesoc-0.5.3.dist-info/RECORD
