Metadata-Version: 2.1
Name: simplesoc
Version: 0.5.3
Summary: A simple Python library for assigning Standard Occupational Classification (SOC) codes to job titles.
Home-page: https://github.com/deino475/simplesoc
Author: Nile Dixon
Author-email: niledixon475@gmail.com
License: GNU GPL-V3
Platform: UNKNOWN
Requires-Python: >=3.6
